trollmoves/__init__.py
trollmoves/client.py
trollmoves/dispatcher.py
trollmoves/fetcher.py
trollmoves/filescleaner.py
trollmoves/heartbeat_monitor.py
trollmoves/hooks.py
trollmoves/logging.py
trollmoves/mirror.py
trollmoves/move_it.py
trollmoves/move_it_base.py
trollmoves/move_it_client.py
trollmoves/move_it_mirror.py
trollmoves/move_it_req.py
trollmoves/move_it_server.py
trollmoves/movers.py
trollmoves/remove_it.py
trollmoves/s3downloader.py
trollmoves/server.py
trollmoves/utils.py
trollmoves/version.py
trollmoves/tests/conftest.py
trollmoves/tests/test_base.py
trollmoves/tests/test_client.py
trollmoves/tests/test_dispatcher.py
trollmoves/tests/test_fetcher.py
trollmoves/tests/test_get_config.py
trollmoves/tests/test_logging.py
trollmoves/tests/test_mirror.py
trollmoves/tests/test_move_it.py
trollmoves/tests/test_movers.py
trollmoves/tests/test_remove_files.py
trollmoves/tests/test_s3downloader.py
trollmoves/tests/test_server.py
trollmoves/tests/test_ssh_server.py
trollmoves/tests/test_utils.py
trollmoves/tests/functional/move_it_server_client.feature
trollmoves/tests/functional/test_move_it_server_client.py
trollmoves-0.17.0.dist-info/METADATA
trollmoves-0.17.0.dist-info/WHEEL
trollmoves-0.17.0.dist-info/entry_points.txt
trollmoves-0.17.0.dist-info/licenses/AUTHORS.md
trollmoves-0.17.0.dist-info/licenses/LICENSE
trollmoves-0.17.0.dist-info/RECORD
