Metadata-Version: 2.4
Name: trollmoves
Version: 0.17.0
Summary: Pytroll file utilities
Project-URL: Homepage, https://github.com/pytroll/trollmoves
Author-email: Martin Raspaud <martin.raspaud@smhi.se>
License:                                  Apache License
License-File: AUTHORS.md
License-File: LICENSE
Classifier: Development Status :: 4 - Beta
Classifier: Intended Audience :: Science/Research
Classifier: License :: OSI Approved :: GNU General Public License v3 or later (GPLv3+)
Classifier: Operating System :: OS Independent
Classifier: Programming Language :: Python
Classifier: Topic :: Scientific/Engineering
Requires-Dist: netifaces-plus
Requires-Dist: posttroll>=1.5.1
Requires-Dist: pyyaml
Requires-Dist: pyzmq
Requires-Dist: trollsift
Requires-Dist: watchdog!=4.0.0
Provides-Extra: all
Requires-Dist: fsspec; extra == 'all'
Requires-Dist: paramiko; extra == 'all'
Requires-Dist: pytroll-collectors>=0.16.0; extra == 'all'
Requires-Dist: pytroll-watchers>=0.6.0; extra == 'all'
Requires-Dist: s3fs; extra == 'all'
Requires-Dist: scp; extra == 'all'
Provides-Extra: docs
Provides-Extra: fetcher
Requires-Dist: pytroll-watchers>=0.6.0; extra == 'fetcher'
Provides-Extra: remote-fs
Requires-Dist: fsspec; extra == 'remote-fs'
Requires-Dist: pytroll-collectors>=0.16.0; extra == 'remote-fs'
Provides-Extra: s3
Requires-Dist: s3fs; extra == 's3'
Provides-Extra: server
Requires-Dist: paramiko; extra == 'server'
Requires-Dist: scp; extra == 'server'
